<?xml version="1.0" encoding="utf-8" ?>
<c2layout>
    <name>Layout 1</name>
    <sid>4007695377652145</sid>
    <event-sheet>FASE</event-sheet>
    <size>
        <width>30000</width>
        <height>480</height>
    </size>
    <margins>
        <horizontal>500</horizontal>
        <vertical>500</vertical>
    </margins>
    <unbounded-scrolling>0</unbounded-scrolling>
    <layers>
        <layer name="Fundo" sid="5493467845860011">
            <initially-visible>1</initially-visible>
            <background-color>255,255,255</background-color>
            <transparent>1</transparent>
            <parallax>
                <x>1</x>
                <y>1</y>
            </parallax>
            <zoom-rate>1</zoom-rate>
            <opacity>1</opacity>
            <force-own-texture>0</force-own-texture>
            <blend-mode>0</blend-mode>
            <effect-fallback>0</effect-fallback>
            <instances>
                <instance type="TiledBackgroundCima" uid="6">
                    <properties>
                        <initial-visibility>Visible</initial-visibility>
                        <hotspot>Top-left</hotspot>
                    </properties>
                    <effect-instances>
                        <effect-instance type="WaterBackground">
                            <parameters>
                                <angle>7</angle>
                                <delta>20</delta>
                                <emboss>0.3</emboss>
                                <frequency>4</frequency>
                                <intensity>3</intensity>
                                <reflectivity>400</reflectivity>
                                <speed>0.1</speed>
                                <x-speed>0.3</x-speed>
                                <y-speed>0.3</y-speed>
                            </parameters>
                        </effect-instance>
                    </effect-instances>
                    <blend-mode>0</blend-mode>
                    <effect-fallback>0</effect-fallback>
                    <world>
                        <x>0</x>
                        <y>0</y>
                        <z>0</z>
                        <width>2371</width>
                        <height>239</height>
                        <depth>0</depth>
                        <hotspotX>0</hotspotX>
                        <hotspotY>0</hotspotY>
                        <angle>0</angle>
                        <opacity>1</opacity>
                    </world>
                </instance>
                <instance type="laser" uid="8">
                    <properties>
                        <initial-visibility>Visible</initial-visibility>
                        <initial-animation>Default</initial-animation>
                        <initial-frame>0</initial-frame>
                        <collisions>Enabled</collisions>
                    </properties>
                    <instance-variables>
                        <qtde>0</qtde>
                    </instance-variables>
                    <behavior-instances>
                        <behavior-instance type="DestroyOutsideLayout" />
                        <behavior-instance type="Bullet">
                            <properties>
                                <speed>700</speed>
                                <acceleration>0</acceleration>
                                <gravity>0</gravity>
                                <bounce-off-solids>No</bounce-off-solids>
                                <set-angle>Yes</set-angle>
                                <initial-state>Enabled</initial-state>
                            </properties>
                        </behavior-instance>
                    </behavior-instances>
                    <blend-mode>0</blend-mode>
                    <effect-fallback>0</effect-fallback>
                    <world>
                        <x>-436</x>
                        <y>787</y>
                        <z>0</z>
                        <width>25</width>
                        <height>4</height>
                        <depth>0</depth>
                        <hotspotX>0.519999981</hotspotX>
                        <hotspotY>0.75</hotspotY>
                        <angle>0</angle>
                        <opacity>1</opacity>
                    </world>
                </instance>
                <instance type="TiledBackgroundBaixo" uid="7">
                    <properties>
                        <initial-visibility>Visible</initial-visibility>
                        <hotspot>Top-left</hotspot>
                    </properties>
                    <effect-instances>
                        <effect-instance type="WaterBackground">
                            <parameters>
                                <angle>7</angle>
                                <delta>20</delta>
                                <emboss>0.3</emboss>
                                <frequency>4</frequency>
                                <intensity>3</intensity>
                                <reflectivity>400</reflectivity>
                                <speed>0.1</speed>
                                <x-speed>0.3</x-speed>
                                <y-speed>0.3</y-speed>
                            </parameters>
                        </effect-instance>
                    </effect-instances>
                    <blend-mode>0</blend-mode>
                    <effect-fallback>0</effect-fallback>
                    <world>
                        <x>0</x>
                        <y>240</y>
                        <z>0</z>
                        <width>1260</width>
                        <height>240</height>
                        <depth>0</depth>
                        <hotspotX>0</hotspotX>
                        <hotspotY>0</hotspotY>
                        <angle>0</angle>
                        <opacity>1</opacity>
                    </world>
                </instance>
                <instance type="gravidade" uid="19">
                    <properties>
                        <initial-visibility>Visible</initial-visibility>
                        <initial-animation>Default</initial-animation>
                        <initial-frame>0</initial-frame>
                        <collisions>Enabled</collisions>
                    </properties>
                    <behavior-instances>
                        <behavior-instance type="Bullet">
                            <properties>
                                <speed>50</speed>
                                <acceleration>0</acceleration>
                                <gravity>0</gravity>
                                <bounce-off-solids>No</bounce-off-solids>
                                <set-angle>Yes</set-angle>
                                <initial-state>Enabled</initial-state>
                            </properties>
                        </behavior-instance>
                        <behavior-instance type="Sine">
                            <properties>
                                <active-on-start>Yes</active-on-start>
                                <movement>Size</movement>
                                <wave>Sine</wave>
                                <period>1</period>
                                <period-random>0</period-random>
                                <period-offset>0</period-offset>
                                <period-offset-random>0</period-offset-random>
                                <magnitude>5</magnitude>
                                <magnitude-random>0</magnitude-random>
                            </properties>
                        </behavior-instance>
                    </behavior-instances>
                    <blend-mode>0</blend-mode>
                    <effect-fallback>0</effect-fallback>
                    <world>
                        <x>301</x>
                        <y>841</y>
                        <z>0</z>
                        <width>50</width>
                        <height>50</height>
                        <depth>0</depth>
                        <hotspotX>0.5</hotspotX>
                        <hotspotY>0.5</hotspotY>
                        <angle>0</angle>
                        <opacity>1</opacity>
                    </world>
                </instance>
                <instance type="alerta" uid="21">
                    <properties>
                        <initial-visibility>Visible</initial-visibility>
                        <initial-animation>Default</initial-animation>
                        <initial-frame>0</initial-frame>
                        <collisions>Enabled</collisions>
                    </properties>
                    <behavior-instances>
                        <behavior-instance type="Bullet">
                            <properties>
                                <speed>400</speed>
                                <acceleration>0</acceleration>
                                <gravity>0</gravity>
                                <bounce-off-solids>No</bounce-off-solids>
                                <set-angle>Yes</set-angle>
                                <initial-state>Disabled</initial-state>
                            </properties>
                        </behavior-instance>
                        <behavior-instance type="DestroyOutsideLayout" />
                    </behavior-instances>
                    <blend-mode>0</blend-mode>
                    <effect-fallback>0</effect-fallback>
                    <world>
                        <x>1</x>
                        <y>807</y>
                        <z>0</z>
                        <width>1007</width>
                        <height>3</height>
                        <depth>0</depth>
                        <hotspotX>0.5</hotspotX>
                        <hotspotY>0.600000024</hotspotY>
                        <angle>0</angle>
                        <opacity>1</opacity>
                    </world>
                </instance>
                <instance type="aviao" uid="18">
                    <properties>
                        <initial-visibility>Visible</initial-visibility>
                        <initial-animation>Default</initial-animation>
                        <initial-frame>0</initial-frame>
                        <collisions>Enabled</collisions>
                    </properties>
                    <instance-variables>
                        <dano>50</dano>
                    </instance-variables>
                    <behavior-instances>
                        <behavior-instance type="Pathfinding">
                            <properties>
                                <cell-size>30</cell-size>
                                <cell-border>-1</cell-border>
                                <obstacles>Solids</obstacles>
                                <max-speed>200</max-speed>
                                <acceleration>1000</acceleration>
                                <deceleration>2000</deceleration>
                                <rotate-speed>135</rotate-speed>
                                <rotate-object>No</rotate-object>
                                <diagonals>Disabled</diagonals>
                                <initial-state>Enabled</initial-state>
                            </properties>
                        </behavior-instance>
                        <behavior-instance type="Bullet">
                            <properties>
                                <speed>100</speed>
                                <acceleration>0</acceleration>
                                <gravity>0</gravity>
                                <bounce-off-solids>No</bounce-off-solids>
                                <set-angle>Yes</set-angle>
                                <initial-state>Enabled</initial-state>
                            </properties>
                        </behavior-instance>
                    </behavior-instances>
                    <blend-mode>0</blend-mode>
                    <effect-fallback>0</effect-fallback>
                    <world>
                        <x>-348</x>
                        <y>962</y>
                        <z>0</z>
                        <width>128</width>
                        <height>32</height>
                        <depth>0</depth>
                        <hotspotX>0.5</hotspotX>
                        <hotspotY>0.5</hotspotY>
                        <angle>0</angle>
                        <opacity>1</opacity>
                    </world>
                </instance>
                <instance type="laserEnemy" uid="23">
                    <properties>
                        <initial-visibility>Visible</initial-visibility>
                        <initial-animation>Default</initial-animation>
                        <initial-frame>0</initial-frame>
                        <collisions>Enabled</collisions>
                    </properties>
                    <instance-variables>
                        <dano>10</dano>
                        <qtde>0</qtde>
                    </instance-variables>
                    <behavior-instances>
                        <behavior-instance type="Pathfinding">
                            <properties>
                                <cell-size>30</cell-size>
                                <cell-border>-1</cell-border>
                                <obstacles>Solids</obstacles>
                                <max-speed>200</max-speed>
                                <acceleration>1000</acceleration>
                                <deceleration>2000</deceleration>
                                <rotate-speed>135</rotate-speed>
                                <rotate-object>No</rotate-object>
                                <diagonals>Disabled</diagonals>
                                <initial-state>Enabled</initial-state>
                            </properties>
                        </behavior-instance>
                        <behavior-instance type="DestroyOutsideLayout" />
                        <behavior-instance type="Bullet">
                            <properties>
                                <speed>700</speed>
                                <acceleration>0</acceleration>
                                <gravity>0</gravity>
                                <bounce-off-solids>No</bounce-off-solids>
                                <set-angle>Yes</set-angle>
                                <initial-state>Enabled</initial-state>
                            </properties>
                        </behavior-instance>
                    </behavior-instances>
                    <blend-mode>0</blend-mode>
                    <effect-fallback>0</effect-fallback>
                    <world>
                        <x>-434</x>
                        <y>842</y>
                        <z>0</z>
                        <width>20</width>
                        <height>5</height>
                        <depth>0</depth>
                        <hotspotX>0.5</hotspotX>
                        <hotspotY>0.600000024</hotspotY>
                        <angle>0</angle>
                        <opacity>1</opacity>
                    </world>
                </instance>
                <instance type="destroçoLaser" uid="24">
                    <properties>
                        <rate>50</rate>
                        <spray-cone>170</spray-cone>
                        <type>One-shot</type>
                        <initial-particle-properties></initial-particle-properties>
                        <speed>60</speed>
                        <size>2</size>
                        <opacity>100</opacity>
                        <grow-rate>0</grow-rate>
                        <x-randomiser>0</x-randomiser>
                        <y-randomiser>0</y-randomiser>
                        <speed-randomiser->0</speed-randomiser->
                        <size-randomiser>0</size-randomiser>
                        <grow-rate-randomiser>0</grow-rate-randomiser>
                        <particle-lifetime-properties></particle-lifetime-properties>
                        <acceleration>-50</acceleration>
                        <gravity>0</gravity>
                        <angle-randomiser>0</angle-randomiser>
                        <speed-randomiser>600</speed-randomiser>
                        <opacity-randomiser>0</opacity-randomiser>
                        <destroy-mode>Fade to invisible</destroy-mode>
                        <timeout>1</timeout>
                    </properties>
                    <blend-mode>0</blend-mode>
                    <effect-fallback>0</effect-fallback>
                    <world>
                        <x>-202</x>
                        <y>883</y>
                        <z>0</z>
                        <width>128</width>
                        <height>128</height>
                        <depth>0</depth>
                        <hotspotX>0</hotspotX>
                        <hotspotY>0.5</hotspotY>
                        <angle>3.141592741</angle>
                        <opacity>1</opacity>
                    </world>
                </instance>
            </instances>
            <effects />
        </layer>
        <layer name="Personagens" sid="3308571351946275">
            <initially-visible>1</initially-visible>
            <background-color>255,255,255</background-color>
            <transparent>1</transparent>
            <parallax>
                <x>1</x>
                <y>1</y>
            </parallax>
            <zoom-rate>1</zoom-rate>
            <opacity>1</opacity>
            <force-own-texture>0</force-own-texture>
            <blend-mode>0</blend-mode>
            <effect-fallback>0</effect-fallback>
            <instances>
                <instance type="personagemPulo" uid="0">
                    <properties>
                        <initial-visibility>Visible</initial-visibility>
                        <initial-animation>Default</initial-animation>
                        <initial-frame>0</initial-frame>
                        <collisions>Enabled</collisions>
                    </properties>
                    <instance-variables>
                        <life>100</life>
                    </instance-variables>
                    <behavior-instances>
                        <behavior-instance type="Platform">
                            <properties>
                                <max-speed>330</max-speed>
                                <acceleration>1500</acceleration>
                                <deceleration>1500</deceleration>
                                <jump-strength>650</jump-strength>
                                <gravity>1500</gravity>
                                <max-fall-speed>1000</max-fall-speed>
                                <default-controls>Yes</default-controls>
                                <initial-state>Enabled</initial-state>
                            </properties>
                        </behavior-instance>
                        <behavior-instance type="Flash" />
                        <behavior-instance type="ScrollTo">
                            <properties>
                                <initial-state>Enabled</initial-state>
                            </properties>
                        </behavior-instance>
                    </behavior-instances>
                    <blend-mode>0</blend-mode>
                    <effect-fallback>0</effect-fallback>
                    <world>
                        <x>66</x>
                        <y>42</y>
                        <z>0</z>
                        <width>64</width>
                        <height>64</height>
                        <depth>0</depth>
                        <hotspotX>0.5</hotspotX>
                        <hotspotY>0.5</hotspotY>
                        <angle>0</angle>
                        <opacity>1</opacity>
                    </world>
                </instance>
                <instance type="personagemTiro" uid="1">
                    <properties>
                        <initial-visibility>Visible</initial-visibility>
                        <initial-animation>Default</initial-animation>
                        <initial-frame>0</initial-frame>
                        <collisions>Enabled</collisions>
                    </properties>
                    <instance-variables>
                        <life>100</life>
                        <flipado>false</flipado>
                    </instance-variables>
                    <behavior-instances>
                        <behavior-instance type="Platform">
                            <properties>
                                <max-speed>330</max-speed>
                                <acceleration>1500</acceleration>
                                <deceleration>1500</deceleration>
                                <jump-strength>650</jump-strength>
                                <gravity>-1500</gravity>
                                <max-fall-speed>1000</max-fall-speed>
                                <default-controls>No</default-controls>
                                <initial-state>Enabled</initial-state>
                            </properties>
                        </behavior-instance>
                        <behavior-instance type="Flash" />
                        <behavior-instance type="ScrollTo">
                            <properties>
                                <initial-state>Enabled</initial-state>
                            </properties>
                        </behavior-instance>
                    </behavior-instances>
                    <blend-mode>0</blend-mode>
                    <effect-fallback>0</effect-fallback>
                    <world>
                        <x>63</x>
                        <y>434</y>
                        <z>0</z>
                        <width>64</width>
                        <height>64</height>
                        <depth>0</depth>
                        <hotspotX>0.5</hotspotX>
                        <hotspotY>0.5</hotspotY>
                        <angle>0</angle>
                        <opacity>1</opacity>
                    </world>
                </instance>
                <instance type="enemy" uid="12">
                    <properties>
                        <initial-visibility>Visible</initial-visibility>
                        <initial-animation>Default</initial-animation>
                        <initial-frame>0</initial-frame>
                        <collisions>Enabled</collisions>
                    </properties>
                    <instance-variables>
                        <dano>50</dano>
                    </instance-variables>
                    <behavior-instances>
                        <behavior-instance type="Pathfinding">
                            <properties>
                                <cell-size>30</cell-size>
                                <cell-border>-1</cell-border>
                                <obstacles>Solids</obstacles>
                                <max-speed>200</max-speed>
                                <acceleration>1000</acceleration>
                                <deceleration>2000</deceleration>
                                <rotate-speed>135</rotate-speed>
                                <rotate-object>No</rotate-object>
                                <diagonals>Disabled</diagonals>
                                <initial-state>Enabled</initial-state>
                            </properties>
                        </behavior-instance>
                        <behavior-instance type="Sine">
                            <properties>
                                <active-on-start>Yes</active-on-start>
                                <movement>Vertical</movement>
                                <wave>Sine</wave>
                                <period>2</period>
                                <period-random>0</period-random>
                                <period-offset>0</period-offset>
                                <period-offset-random>0</period-offset-random>
                                <magnitude>10</magnitude>
                                <magnitude-random>0</magnitude-random>
                            </properties>
                        </behavior-instance>
                    </behavior-instances>
                    <blend-mode>0</blend-mode>
                    <effect-fallback>0</effect-fallback>
                    <world>
                        <x>-63</x>
                        <y>856</y>
                        <z>0</z>
                        <width>128</width>
                        <height>128</height>
                        <depth>0</depth>
                        <hotspotX>0.5</hotspotX>
                        <hotspotY>0.5</hotspotY>
                        <angle>0</angle>
                        <opacity>1</opacity>
                    </world>
                </instance>
                <instance type="spawnador" uid="13">
                    <properties>
                        <initial-visibility>Invisible</initial-visibility>
                        <initial-animation>Default</initial-animation>
                        <initial-frame>0</initial-frame>
                        <collisions>Enabled</collisions>
                    </properties>
                    <blend-mode>0</blend-mode>
                    <effect-fallback>0</effect-fallback>
                    <world>
                        <x>795</x>
                        <y>238</y>
                        <z>0</z>
                        <width>40.422767639</width>
                        <height>40.422767639</height>
                        <depth>0</depth>
                        <hotspotX>0.5</hotspotX>
                        <hotspotY>0.5</hotspotY>
                        <angle>0</angle>
                        <opacity>1</opacity>
                    </world>
                </instance>
                <instance type="spawnador2" uid="15">
                    <properties>
                        <initial-visibility>Invisible</initial-visibility>
                        <initial-animation>Default</initial-animation>
                        <initial-frame>0</initial-frame>
                        <collisions>Enabled</collisions>
                    </properties>
                    <blend-mode>0</blend-mode>
                    <effect-fallback>0</effect-fallback>
                    <world>
                        <x>843</x>
                        <y>240</y>
                        <z>0</z>
                        <width>50</width>
                        <height>50</height>
                        <depth>0</depth>
                        <hotspotX>0.5</hotspotX>
                        <hotspotY>0.5</hotspotY>
                        <angle>0</angle>
                        <opacity>1</opacity>
                    </world>
                </instance>
                <instance type="FundoPretp" uid="11">
                    <properties>
                        <initial-visibility>Visible</initial-visibility>
                        <hotspot>Center</hotspot>
                    </properties>
                    <behavior-instances>
                        <behavior-instance type="Solid">
                            <properties>
                                <initial-state>Enabled</initial-state>
                            </properties>
                        </behavior-instance>
                    </behavior-instances>
                    <blend-mode>0</blend-mode>
                    <effect-fallback>0</effect-fallback>
                    <world>
                        <x>63</x>
                        <y>851</y>
                        <z>0</z>
                        <width>50</width>
                        <height>50</height>
                        <depth>0</depth>
                        <hotspotX>0.5</hotspotX>
                        <hotspotY>0.5</hotspotY>
                        <angle>0</angle>
                        <opacity>1</opacity>
                    </world>
                </instance>
                <instance type="turret" uid="22">
                    <properties>
                        <initial-visibility>Visible</initial-visibility>
                        <initial-animation>Default</initial-animation>
                        <initial-frame>0</initial-frame>
                        <collisions>Enabled</collisions>
                    </properties>
                    <behavior-instances>
                        <behavior-instance type="Turret">
                            <properties>
                                <range>500</range>
                                <rate-of-fire>0.3</rate-of-fire>
                                <rotate>Yes</rotate>
                                <rotate-speed>180</rotate-speed>
                                <target-mode>First in range</target-mode>
                                <predictive-aim>No</predictive-aim>
                                <projectile-speed>200</projectile-speed>
                                <initial-state>Enabled</initial-state>
                            </properties>
                        </behavior-instance>
                    </behavior-instances>
                    <blend-mode>0</blend-mode>
                    <effect-fallback>0</effect-fallback>
                    <world>
                        <x>290</x>
                        <y>956</y>
                        <z>0</z>
                        <width>32</width>
                        <height>32</height>
                        <depth>0</depth>
                        <hotspotX>0.5</hotspotX>
                        <hotspotY>0.5</hotspotY>
                        <angle>0</angle>
                        <opacity>1</opacity>
                    </world>
                </instance>
                <instance type="canhao" uid="17">
                    <properties>
                        <initial-visibility>Visible</initial-visibility>
                        <initial-animation>Default</initial-animation>
                        <initial-frame>0</initial-frame>
                        <collisions>Enabled</collisions>
                    </properties>
                    <instance-variables>
                        <dano>30</dano>
                    </instance-variables>
                    <behavior-instances>
                        <behavior-instance type="Pathfinding">
                            <properties>
                                <cell-size>30</cell-size>
                                <cell-border>-1</cell-border>
                                <obstacles>Solids</obstacles>
                                <max-speed>200</max-speed>
                                <acceleration>1000</acceleration>
                                <deceleration>2000</deceleration>
                                <rotate-speed>135</rotate-speed>
                                <rotate-object>No</rotate-object>
                                <diagonals>Disabled</diagonals>
                                <initial-state>Disabled</initial-state>
                            </properties>
                        </behavior-instance>
                        <behavior-instance type="Bullet">
                            <properties>
                                <speed>600</speed>
                                <acceleration>0</acceleration>
                                <gravity>0</gravity>
                                <bounce-off-solids>No</bounce-off-solids>
                                <set-angle>Yes</set-angle>
                                <initial-state>Enabled</initial-state>
                            </properties>
                        </behavior-instance>
                        <behavior-instance type="DestroyOutsideLayout" />
                    </behavior-instances>
                    <blend-mode>0</blend-mode>
                    <effect-fallback>0</effect-fallback>
                    <world>
                        <x>442</x>
                        <y>827</y>
                        <z>0</z>
                        <width>66</width>
                        <height>18</height>
                        <depth>0</depth>
                        <hotspotX>0.484848499</hotspotX>
                        <hotspotY>0.555555582</hotspotY>
                        <angle>0</angle>
                        <opacity>1</opacity>
                    </world>
                </instance>
            </instances>
            <effects />
        </layer>
        <layer name="Div" sid="6004152407230677">
            <initially-visible>1</initially-visible>
            <background-color>255,255,255</background-color>
            <transparent>1</transparent>
            <parallax>
                <x>1</x>
                <y>1</y>
            </parallax>
            <zoom-rate>1</zoom-rate>
            <opacity>1</opacity>
            <force-own-texture>0</force-own-texture>
            <blend-mode>0</blend-mode>
            <effect-fallback>0</effect-fallback>
            <instances>
                <instance type="AguaBaixo" uid="16">
                    <properties>
                        <initial-visibility>Visible</initial-visibility>
                        <hotspot>Top-left</hotspot>
                    </properties>
                    <effect-instances>
                        <effect-instance type="Water">
                            <parameters>
                                <angle>7</angle>
                                <delta>20</delta>
                                <emboss>0.3</emboss>
                                <frequency>4</frequency>
                                <intensity>3</intensity>
                                <reflectivity>400</reflectivity>
                                <speed>0.1</speed>
                                <x-speed>0.3</x-speed>
                                <y-speed>0.3</y-speed>
                            </parameters>
                        </effect-instance>
                    </effect-instances>
                    <blend-mode>0</blend-mode>
                    <effect-fallback>0</effect-fallback>
                    <world>
                        <x>0</x>
                        <y>240</y>
                        <z>0</z>
                        <width>800</width>
                        <height>240</height>
                        <depth>0</depth>
                        <hotspotX>0</hotspotX>
                        <hotspotY>0</hotspotY>
                        <angle>0</angle>
                        <opacity>1</opacity>
                    </world>
                </instance>
                <instance type="FundoPretp" uid="2">
                    <properties>
                        <initial-visibility>Visible</initial-visibility>
                        <hotspot>Center</hotspot>
                    </properties>
                    <behavior-instances>
                        <behavior-instance type="Solid">
                            <properties>
                                <initial-state>Enabled</initial-state>
                            </properties>
                        </behavior-instance>
                    </behavior-instances>
                    <blend-mode>0</blend-mode>
                    <effect-fallback>0</effect-fallback>
                    <world>
                        <x>400</x>
                        <y>606</y>
                        <z>0</z>
                        <width>800</width>
                        <height>272</height>
                        <depth>0</depth>
                        <hotspotX>0.5</hotspotX>
                        <hotspotY>0.5</hotspotY>
                        <angle>0</angle>
                        <opacity>1</opacity>
                    </world>
                </instance>
                <instance type="FundoPretp" uid="3">
                    <properties>
                        <initial-visibility>Visible</initial-visibility>
                        <hotspot>Center</hotspot>
                    </properties>
                    <behavior-instances>
                        <behavior-instance type="Solid">
                            <properties>
                                <initial-state>Enabled</initial-state>
                            </properties>
                        </behavior-instance>
                    </behavior-instances>
                    <blend-mode>0</blend-mode>
                    <effect-fallback>0</effect-fallback>
                    <world>
                        <x>400</x>
                        <y>-139</y>
                        <z>0</z>
                        <width>800</width>
                        <height>298</height>
                        <depth>0</depth>
                        <hotspotX>0.5</hotspotX>
                        <hotspotY>0.5</hotspotY>
                        <angle>0</angle>
                        <opacity>1</opacity>
                    </world>
                </instance>
                <instance type="FundoPretp" uid="4">
                    <properties>
                        <initial-visibility>Visible</initial-visibility>
                        <hotspot>Center</hotspot>
                    </properties>
                    <behavior-instances>
                        <behavior-instance type="Solid">
                            <properties>
                                <initial-state>Enabled</initial-state>
                            </properties>
                        </behavior-instance>
                    </behavior-instances>
                    <blend-mode>0</blend-mode>
                    <effect-fallback>0</effect-fallback>
                    <world>
                        <x>252</x>
                        <y>240</y>
                        <z>0</z>
                        <width>1096</width>
                        <height>40</height>
                        <depth>0</depth>
                        <hotspotX>0.5</hotspotX>
                        <hotspotY>0.5</hotspotY>
                        <angle>0</angle>
                        <opacity>1</opacity>
                    </world>
                </instance>
            </instances>
            <effects />
        </layer>
        <layer name="HUD" sid="7614273639760556">
            <initially-visible>1</initially-visible>
            <background-color>255,255,255</background-color>
            <transparent>1</transparent>
            <parallax>
                <x>0</x>
                <y>0</y>
            </parallax>
            <zoom-rate>1</zoom-rate>
            <opacity>1</opacity>
            <force-own-texture>0</force-own-texture>
            <blend-mode>0</blend-mode>
            <effect-fallback>0</effect-fallback>
            <instances>
                <instance type="moldura" uid="30">
                    <properties>
                        <initial-visibility>Visible</initial-visibility>
                        <initial-animation>Default</initial-animation>
                        <initial-frame>0</initial-frame>
                        <collisions>Enabled</collisions>
                    </properties>
                    <blend-mode>0</blend-mode>
                    <effect-fallback>0</effect-fallback>
                    <world>
                        <x>57</x>
                        <y>231</y>
                        <z>0</z>
                        <width>200</width>
                        <height>18</height>
                        <depth>0</depth>
                        <hotspotX>0</hotspotX>
                        <hotspotY>0</hotspotY>
                        <angle>0</angle>
                        <opacity>1</opacity>
                    </world>
                </instance>
                <instance type="moldura" uid="31">
                    <properties>
                        <initial-visibility>Visible</initial-visibility>
                        <initial-animation>Default</initial-animation>
                        <initial-frame>0</initial-frame>
                        <collisions>Enabled</collisions>
                    </properties>
                    <blend-mode>0</blend-mode>
                    <effect-fallback>0</effect-fallback>
                    <world>
                        <x>294</x>
                        <y>231</y>
                        <z>0</z>
                        <width>200</width>
                        <height>18</height>
                        <depth>0</depth>
                        <hotspotX>0</hotspotX>
                        <hotspotY>0</hotspotY>
                        <angle>0</angle>
                        <opacity>1</opacity>
                    </world>
                </instance>
                <instance type="moldura" uid="32">
                    <properties>
                        <initial-visibility>Visible</initial-visibility>
                        <initial-animation>Default</initial-animation>
                        <initial-frame>0</initial-frame>
                        <collisions>Enabled</collisions>
                    </properties>
                    <blend-mode>0</blend-mode>
                    <effect-fallback>0</effect-fallback>
                    <world>
                        <x>531</x>
                        <y>231</y>
                        <z>0</z>
                        <width>200</width>
                        <height>18</height>
                        <depth>0</depth>
                        <hotspotX>0</hotspotX>
                        <hotspotY>0</hotspotY>
                        <angle>0</angle>
                        <opacity>1</opacity>
                    </world>
                </instance>
                <instance type="9patch" uid="28">
                    <properties>
                        <left-margin>2</left-margin>
                        <right-margin>2</right-margin>
                        <top-margin>2</top-margin>
                        <bottom-margin>2</bottom-margin>
                        <edges>Stretch</edges>
                        <fill>Stretch</fill>
                        <initial-visibility>Visible</initial-visibility>
                        <hotspot>Top-left</hotspot>
                        <seams>Overlap</seams>
                    </properties>
                    <blend-mode>0</blend-mode>
                    <effect-fallback>0</effect-fallback>
                    <world>
                        <x>57</x>
                        <y>231</y>
                        <z>0</z>
                        <width>200</width>
                        <height>18</height>
                        <depth>0</depth>
                        <hotspotX>0</hotspotX>
                        <hotspotY>0</hotspotY>
                        <opacity>1</opacity>
                    </world>
                </instance>
                <instance type="9patch2" uid="20">
                    <properties>
                        <left-margin>2</left-margin>
                        <right-margin>2</right-margin>
                        <top-margin>2</top-margin>
                        <bottom-margin>2</bottom-margin>
                        <edges>Stretch</edges>
                        <fill>Stretch</fill>
                        <initial-visibility>Visible</initial-visibility>
                        <hotspot>Top-left</hotspot>
                        <seams>Overlap</seams>
                    </properties>
                    <blend-mode>0</blend-mode>
                    <effect-fallback>0</effect-fallback>
                    <world>
                        <x>531</x>
                        <y>231</y>
                        <z>0</z>
                        <width>200</width>
                        <height>18</height>
                        <depth>0</depth>
                        <hotspotX>0</hotspotX>
                        <hotspotY>0</hotspotY>
                        <opacity>1</opacity>
                    </world>
                </instance>
                <instance type="9patch3" uid="25">
                    <properties>
                        <left-margin>2</left-margin>
                        <right-margin>2</right-margin>
                        <top-margin>2</top-margin>
                        <bottom-margin>2</bottom-margin>
                        <edges>Stretch</edges>
                        <fill>Stretch</fill>
                        <initial-visibility>Visible</initial-visibility>
                        <hotspot>Top-left</hotspot>
                        <seams>Overlap</seams>
                    </properties>
                    <blend-mode>0</blend-mode>
                    <effect-fallback>0</effect-fallback>
                    <world>
                        <x>294</x>
                        <y>231</y>
                        <z>0</z>
                        <width>200</width>
                        <height>18</height>
                        <depth>0</depth>
                        <hotspotX>0</hotspotX>
                        <hotspotY>0</hotspotY>
                        <opacity>1</opacity>
                    </world>
                </instance>
                <instance type="FundoPretp2" uid="26">
                    <properties>
                        <initial-visibility>Visible</initial-visibility>
                        <hotspot>Center</hotspot>
                    </properties>
                    <behavior-instances>
                        <behavior-instance type="Solid">
                            <properties>
                                <initial-state>Enabled</initial-state>
                            </properties>
                        </behavior-instance>
                    </behavior-instances>
                    <blend-mode>0</blend-mode>
                    <effect-fallback>0</effect-fallback>
                    <world>
                        <x>127</x>
                        <y>862</y>
                        <z>0</z>
                        <width>50</width>
                        <height>50</height>
                        <depth>0</depth>
                        <hotspotX>0.5</hotspotX>
                        <hotspotY>0.5</hotspotY>
                        <angle>0</angle>
                        <opacity>1</opacity>
                    </world>
                </instance>
                <instance type="destroçoParede" uid="27">
                    <properties>
                        <rate>50</rate>
                        <spray-cone>360</spray-cone>
                        <type>One-shot</type>
                        <initial-particle-properties></initial-particle-properties>
                        <speed>60</speed>
                        <size>2</size>
                        <opacity>100</opacity>
                        <grow-rate>0</grow-rate>
                        <x-randomiser>0</x-randomiser>
                        <y-randomiser>0</y-randomiser>
                        <speed-randomiser->0</speed-randomiser->
                        <size-randomiser>0</size-randomiser>
                        <grow-rate-randomiser>0</grow-rate-randomiser>
                        <particle-lifetime-properties></particle-lifetime-properties>
                        <acceleration>-50</acceleration>
                        <gravity>0</gravity>
                        <angle-randomiser>0</angle-randomiser>
                        <speed-randomiser>600</speed-randomiser>
                        <opacity-randomiser>0</opacity-randomiser>
                        <destroy-mode>Fade to invisible</destroy-mode>
                        <timeout>1</timeout>
                    </properties>
                    <blend-mode>0</blend-mode>
                    <effect-fallback>0</effect-fallback>
                    <world>
                        <x>-14</x>
                        <y>928</y>
                        <z>0</z>
                        <width>128</width>
                        <height>128</height>
                        <depth>0</depth>
                        <hotspotX>0</hotspotX>
                        <hotspotY>0.5</hotspotY>
                        <angle>3.141592741</angle>
                        <opacity>1</opacity>
                    </world>
                </instance>
            </instances>
            <effects />
        </layer>
    </layers>
    <nonworld-instances />
    <effects />
</c2layout>
