<?xml version="1.0" encoding="utf-8" ?>
<c2eventsheet>
    <!--All the 'name' attributes are ignored by Construct 2 - they are there for readability only.-->
    <name>Joystick</name>
    <events>
        <variable comment="0 para Runner, 1 para Jumper" constant="0" name="gameMode" sid="8977558681896338" static="0" type="number">0</variable>
        <event-block sid="6726915460588192">
            <conditions>
                <condition id="-14" name="Compare variable" sid="8230316041969211" type="System">
                    <param id="0" name="Variable">gameMode</param>
                    <param id="1" name="Comparison">0</param>
                    <param id="2" name="Value">0</param>
                </condition>
            </conditions>
            <actions />
            <sub-events>
                <event-block any="1" sid="4182355342662315">
                    <conditions>
                        <condition id="5" name="Compare axis" sid="250938915161593" type="Gamepad">
                            <param id="0" name="Gamepad">0</param>
                            <param id="1" name="Axis">0</param>
                            <param id="2" name="Comparison">2</param>
                            <param id="3" name="Value">0</param>
                        </condition>
                        <condition id="3" name="Is button down" sid="1486834191820709" type="Gamepad">
                            <param id="0" name="Gamepad">0</param>
                            <param id="1" name="Button">14</param>
                        </condition>
                    </conditions>
                    <actions>
                        <action behavior="Platform" id="7" name="Simulate control" sid="7174892434982378" type="personagemPulo">
                            <param id="0" name="Control">0</param>
                        </action>
                        <action id="7" name="Set mirrored" sid="2868198185858771" type="personagemPulo">
                            <param id="0" name="State">0</param>
                        </action>
                    </actions>
                </event-block>
                <event-block any="1" sid="9115181500768988">
                    <conditions>
                        <condition id="5" name="Compare axis" sid="7868317102008628" type="Gamepad">
                            <param id="0" name="Gamepad">0</param>
                            <param id="1" name="Axis">0</param>
                            <param id="2" name="Comparison">4</param>
                            <param id="3" name="Value">0</param>
                        </condition>
                        <condition id="3" name="Is button down" sid="6577782061584094" type="Gamepad">
                            <param id="0" name="Gamepad">0</param>
                            <param id="1" name="Button">15</param>
                        </condition>
                    </conditions>
                    <actions>
                        <action behavior="Platform" id="7" name="Simulate control" sid="3948655656471028" type="personagemPulo">
                            <param id="0" name="Control">1</param>
                        </action>
                        <action id="7" name="Set mirrored" sid="6950826633306081" type="personagemPulo">
                            <param id="0" name="State">1</param>
                        </action>
                    </actions>
                </event-block>
                <event-block any="1" sid="5969572008102172">
                    <conditions>
                        <condition id="6" name="On button pressed" sid="2331015668085798" type="Gamepad">
                            <param id="0" name="Gamepad">0</param>
                            <param id="1" name="Button">12</param>
                        </condition>
                        <condition id="6" name="On button pressed" sid="1748671716944757" type="Gamepad">
                            <param id="0" name="Gamepad">0</param>
                            <param id="1" name="Button">0</param>
                        </condition>
                    </conditions>
                    <actions>
                        <action behavior="Platform" id="7" name="Simulate control" sid="6402853389529678" type="personagemPulo">
                            <param id="0" name="Control">2</param>
                        </action>
                    </actions>
                </event-block>
                <event-block sid="2282097011801678">
                    <conditions>
                        <condition id="6" name="On button pressed" sid="4854409202470149" type="Gamepad">
                            <param id="0" name="Gamepad">0</param>
                            <param id="1" name="Button">7</param>
                        </condition>
                    </conditions>
                    <actions />
                </event-block>
            </sub-events>
        </event-block>
        <event-block sid="8007277444353291">
            <conditions>
                <condition id="-14" name="Compare variable" sid="1252599192261558" type="System">
                    <param id="0" name="Variable">gameMode</param>
                    <param id="1" name="Comparison">0</param>
                    <param id="2" name="Value">0</param>
                </condition>
            </conditions>
            <actions />
            <sub-events>
                <event-block any="1" sid="834218980828882">
                    <conditions>
                        <condition id="5" name="Compare axis" sid="2261875586711233" type="Gamepad">
                            <param id="0" name="Gamepad">1</param>
                            <param id="1" name="Axis">0</param>
                            <param id="2" name="Comparison">2</param>
                            <param id="3" name="Value">0</param>
                        </condition>
                        <condition id="3" name="Is button down" sid="3501183219923666" type="Gamepad">
                            <param id="0" name="Gamepad">1</param>
                            <param id="1" name="Button">14</param>
                        </condition>
                    </conditions>
                    <actions>
                        <action behavior="Platform" id="7" name="Simulate control" sid="4773355796898487" type="personagemTiro">
                            <param id="0" name="Control">0</param>
                        </action>
                        <action id="7" name="Set mirrored" sid="7944835018421044" type="personagemTiro">
                            <param id="0" name="State">0</param>
                        </action>
                    </actions>
                </event-block>
                <event-block any="1" sid="5116490227123936">
                    <conditions>
                        <condition id="5" name="Compare axis" sid="2190792692686805" type="Gamepad">
                            <param id="0" name="Gamepad">1</param>
                            <param id="1" name="Axis">0</param>
                            <param id="2" name="Comparison">4</param>
                            <param id="3" name="Value">0</param>
                        </condition>
                        <condition id="3" name="Is button down" sid="6372624140691947" type="Gamepad">
                            <param id="0" name="Gamepad">1</param>
                            <param id="1" name="Button">15</param>
                        </condition>
                    </conditions>
                    <actions>
                        <action behavior="Platform" id="7" name="Simulate control" sid="3611241922826222" type="personagemTiro">
                            <param id="0" name="Control">1</param>
                        </action>
                        <action id="7" name="Set mirrored" sid="1144855685850617" type="personagemTiro">
                            <param id="0" name="State">1</param>
                        </action>
                    </actions>
                </event-block>
                <event-block any="1" sid="6515584282949422">
                    <conditions>
                        <condition id="6" name="On button pressed" sid="4993394327909154" type="Gamepad">
                            <param id="0" name="Gamepad">1</param>
                            <param id="1" name="Button">12</param>
                        </condition>
                        <condition id="6" name="On button pressed" sid="8964921027347171" type="Gamepad">
                            <param id="0" name="Gamepad">1</param>
                            <param id="1" name="Button">0</param>
                        </condition>
                    </conditions>
                    <actions />
                </event-block>
                <event-block sid="7583550683313394">
                    <conditions>
                        <condition id="6" name="On button pressed" sid="8216852133251598" type="Gamepad">
                            <param id="0" name="Gamepad">1</param>
                            <param id="1" name="Button">7</param>
                        </condition>
                    </conditions>
                    <actions>
                        <action id="0" name="Call function" sid="9599109220617411" type="Function">
                            <param id="0" name="Name">&quot;atirar&quot;</param>
                            <param id="1" name="Parameter {n}"></param>
                        </action>
                    </actions>
                </event-block>
            </sub-events>
        </event-block>
    </events>
</c2eventsheet>
